<?xml version="1.0" encoding="utf-8" ?>
<dwsync>
<file name="ajax-loader.gif" server="ftp.s46.freehost.com.ua//www.oknaidveri.com.ua//" local="131567318400000000" remote="131567318400000000" />
<file name="appointment-blue.png" server="ftp.s46.freehost.com.ua//www.oknaidveri.com.ua//" local="131567318400000000" remote="131567318400000000" />
<file name="appointment-green.png" server="ftp.s46.freehost.com.ua//www.oknaidveri.com.ua//" local="131567318400000000" remote="131567318400000000" />
<file name="appointment-mandy.png" server="ftp.s46.freehost.com.ua//www.oknaidveri.com.ua//" local="131567318400000000" remote="131567318400000000" />
<file name="appointment-red.png" server="ftp.s46.freehost.com.ua//www.oknaidveri.com.ua//" local="131567318400000000" remote="131567318400000000" />
<file name="appointment-wordpress.png" server="ftp.s46.freehost.com.ua//www.oknaidveri.com.ua//" local="131567318400000000" remote="131567318400000000" />
<file name="appointment.png" server="ftp.s46.freehost.com.ua//www.oknaidveri.com.ua//" local="131567318400000000" remote="131567318400000000" />
<file name="assign-home.gif" server="ftp.s46.freehost.com.ua//www.oknaidveri.com.ua//" local="131567318400000000" remote="131567318400000000" />
<file name="create-home.gif" server="ftp.s46.freehost.com.ua//www.oknaidveri.com.ua//" local="131567318400000000" remote="131567318400000000" />
</dwsync>